{
    "buttons": [
        {
            "button": "My Check-In",
            "icon": "calendar"
        },
        {
            "button": "Take an Exam",
            "icon": "university"
        },
        {
            "button": "Exam Results",
            "icon": "poll"
        },
        {
            "button": "Classes",
            "icon": "open-book"
        },
        {
            "button": "Home Work",
            "icon": "university"
        },
        {
            "button": "HW Results",
            "icon": "edit"
        },
        {
            "button": "Resources",
            "icon": "file-pdf"
        },
        {
            "button": "Speakings",
            "icon": "microphone"
        },
        {
            "button": "Speaking Reviewa",
            "icon": "star"
        },
        {
            "button": "Listenings",
            "icon": "headphones"
        },
        {
            "button": "Essays",
            "icon": "file-pdf"
        },
        {
            "button": "Essay Reviews",
            "icon": "star"
        }
    ]
}